database_num_sort/__init__.py
database_num_sort/sort.py
database_num_sort-0.0.1.dist-info/METADATA
database_num_sort-0.0.1.dist-info/WHEEL
database_num_sort-0.0.1.dist-info/top_level.txt
database_num_sort-0.0.1.dist-info/RECORD
